ppget/__init__.py
ppget/cli.py
ppget/output.py
ppget/search.py
ppget/xml_extractor.py
ppget-0.1.9.dist-info/METADATA
ppget-0.1.9.dist-info/WHEEL
ppget-0.1.9.dist-info/entry_points.txt
ppget-0.1.9.dist-info/licenses/LICENSE
ppget-0.1.9.dist-info/RECORD
