Metadata-Version: 2.4
Name: ppget
Version: 0.1.9
Summary: A simple CLI tool to download PubMed articles without the complexity of EDirect
Project-URL: Homepage, https://github.com/masaki39/ppget
Project-URL: Repository, https://github.com/masaki39/ppget
Project-URL: Issues, https://github.com/masaki39/ppget/issues
Author-email: masaki39 <masa21gifus@gmail.com>
License: MIT
License-File: LICENSE
Keywords: cli,literature,medicine,papers,pubmed,research,search
Classifier: Development Status :: 3 - Alpha
Classifier: Intended Audience :: Healthcare Industry
Classifier: Intended Audience :: Science/Research
Classifier: License :: OSI Approved :: MIT License
Classifier: Programming Language :: Python :: 3
Classifier: Programming Language :: Python :: 3.12
Classifier: Topic :: Scientific/Engineering :: Medical Science Apps.
Classifier: Topic :: Utilities
Requires-Python: >=3.12
Requires-Dist: pymed-paperscraper<2.0.0,>=1.0.5
Provides-Extra: dev
Requires-Dist: pytest>=7.0.0; extra == 'dev'
Requires-Dist: ruff>=0.1.0; extra == 'dev'
